more_than_inference/__init__.py
more_than_inference/main.py
more_than_inference/runs.py
more_than_inference/client/__init__.py
more_than_inference/datas/__init__.py
more_than_inference/datas/object_detection.py
more_than_inference/extensions/__init__.py
more_than_inference/extensions/fastapi/__init__.py
more_than_inference/extensions/fastapi/server.py
more_than_inference/extensions/fastapi/server_base.py
more_than_inference/extensions/nvml/__init__.py
more_than_inference/extensions/zmq/__init__.py
more_than_inference/extensions/zmq/cs_base.py
more_than_inference/extensions/zmq/object_detection.py
more_than_inference/inference/__init__.py
more_than_inference/inference/image_generation.py
more_than_inference/inference/image_generation.pyi
more_than_inference/inference/meta.py
more_than_inference/inference/object_detection.py
more_than_inference/inference/object_detection.pyi
more_than_inference/inference/universial_detection.py
more_than_inference/protos/__init__.py
more_than_inference/protos/data.proto
more_than_inference/protos/data_pb2.py
more_than_inference/protos/data_pb2.pyi
more_than_inference/protos/node.proto
more_than_inference/protos/node_pb2.py
more_than_inference/protos/node_pb2.pyi
more_than_inference/protos/object_detection.proto
more_than_inference/protos/object_detection_pb2.py
more_than_inference/protos/object_detection_pb2.pyi
more_than_inference/protos/pipeline.proto
more_than_inference/protos/pipeline_pb2.py
more_than_inference/protos/pipeline_pb2.pyi
more_than_inference/protos/resource.proto
more_than_inference/protos/resource_pb2.py
more_than_inference/protos/resource_pb2.pyi
more_than_inference/server/__init__.py
more_than_inference/utils/__init__.py
more_than_inference/utils/build_proto.py
more_than_inference/utils/fix_bug39959.py
more_than_inference/utils/logging.py
more_than_inference/utils/module_functions.py
more_than_inference/utils/parser.py
more_than_inference/utils/parser.pyi
more_than_inference/utils/register.py
more_than_inference-1.0.2.1.dist-info/METADATA
more_than_inference-1.0.2.1.dist-info/WHEEL
more_than_inference-1.0.2.1.dist-info/entry_points.txt
more_than_inference-1.0.2.1.dist-info/top_level.txt
more_than_inference-1.0.2.1.dist-info/RECORD
